appchance_sections/__init__.py
appchance_sections/admin.py
appchance_sections/apps.py
appchance_sections/cache.py
appchance_sections/conf.py
appchance_sections/filtersets.py
appchance_sections/forms.py
appchance_sections/models.py
appchance_sections/receivers.py
appchance_sections/serializers.py
appchance_sections/urls.py
appchance_sections/utils.py
appchance_sections/views.py
django_appchance_sections-0.3.dist-info/LICENCE
django_appchance_sections-0.3.dist-info/METADATA
django_appchance_sections-0.3.dist-info/WHEEL
django_appchance_sections-0.3.dist-info/top_level.txt
django_appchance_sections-0.3.dist-info/RECORD
