Metadata-Version: 2.1
Name: django-appchance-sections
Version: 0.3
Summary: A Django application containing a set of abstract classes to implement a set of highly manageable sections with any content
Home-page: https://bitbucket.org/appchance/appchance-sections/
Author: Zbigniew Heintze
Author-email: zheintze@gmail.com
License: MIT
Classifier: Environment :: Web Environment
Classifier: Framework :: Django
Classifier: Framework :: Django :: 3.0
Classifier: Intended Audience :: Developers
Classifier: License :: OSI Approved :: MIT License
Classifier: Operating System :: OS Independent
Classifier: Programming Language :: Python
Classifier: Programming Language :: Python :: 3
Classifier: Programming Language :: Python :: 3 :: Only
Classifier: Topic :: Internet :: WWW/HTTP
Classifier: Topic :: Internet :: WWW/HTTP :: Dynamic Content
Requires-Python: >=3.7
License-File: LICENCE
Requires-Dist: djangorestframework (>=3.11.0)
Requires-Dist: django-filter (>=2.4.0)
